meraki_rma/__init__.py
meraki_rma/rma.py
meraki_rma-0.1.19.dist-info/WHEEL
meraki_rma-0.1.19.dist-info/METADATA
meraki_rma-0.1.19.dist-info/RECORD
