Metadata-Version: 2.1
Name: meraki-rma
Version: 0.1.19
Summary: Library to make Meraki RMAs easy and programmatic.
Home-page: https://github.com/thomaschristory/meraki_rma
Keywords: meraki,dashboard,cisco,python
Author: Thomas Christory
Requires-Python: >=3.8,<4.0
Classifier: Programming Language :: Python :: 3
Classifier: Programming Language :: Python :: 3.10
Classifier: Programming Language :: Python :: 3.8
Classifier: Programming Language :: Python :: 3.9
Requires-Dist: meraki
Requires-Dist: meraki-dashboard-connect (>=0.1.1,<0.2.0)
Requires-Dist: meraki-env (>=0.1.1,<0.2.0)
Requires-Dist: meraki-exception (>=0.1.1,<0.2.0)
Requires-Dist: rich
Requires-Dist: typer
Project-URL: Bug Tracker, https://github.com/thomaschristory/meraki_rma/issues
